mendelbrot/__init__.py
mendelbrot/bcftools_interpreter.py
mendelbrot/pedigree_parser.py
mendelbrot-0.0.3.dist-info/METADATA
mendelbrot-0.0.3.dist-info/WHEEL
mendelbrot-0.0.3.dist-info/licenses/LICENSE
mendelbrot-0.0.3.dist-info/RECORD
