Metadata-Version: 2.4
Name: mendelbrot
Version: 0.0.3
Summary: A really simple Pedigree Parser
Project-URL: Repository, https://github.com/MattWellie/mendelbrot
License-Expression: MIT
License-File: LICENSE
Classifier: Environment :: Console
Classifier: Intended Audience :: Science/Research
Classifier: Natural Language :: English
Classifier: Operating System :: Unix
Classifier: Programming Language :: Python
Classifier: Topic :: Scientific/Engineering
Classifier: Topic :: Scientific/Engineering :: Bio-Informatics
Requires-Python: >3.8
Requires-Dist: cloudpathlib[all]
Requires-Dist: loguru
Provides-Extra: dev
Requires-Dist: bump-my-version; extra == 'dev'
Requires-Dist: pre-commit; extra == 'dev'
Requires-Dist: pytest; extra == 'dev'
